Metadata-Version: 2.4
Name: solpolpy
Version: 0.5.0
Summary: Solar polarization resolver for any instrument
Author-email: "J. Marcus Hughes" <mhughes@boulder.swri.edu>, "Matthew J. West" <mwest@boulder.swri.edu>, Ritesh Patel <ritesh.patel@swri.org>, "Bryce M. Walbridge" <bmw39@calvin.edu>, Chris Lowder <chris.lowder@swri.org>
Classifier: Programming Language :: Python :: 3
Classifier: License :: OSI Approved :: MIT License
Classifier: Operating System :: OS Independent
Requires-Python: >=3.11
License-File: LICENSE.txt
Requires-Dist: sunpy
Requires-Dist: astropy
Requires-Dist: numpy
Requires-Dist: matplotlib
Requires-Dist: networkx
Requires-Dist: ndcube
Requires-Dist: sunkit_image
Provides-Extra: test
Requires-Dist: pytest; extra == "test"
Requires-Dist: coverage; extra == "test"
Requires-Dist: pytest-cov; extra == "test"
Requires-Dist: ruff; extra == "test"
Provides-Extra: docs
Requires-Dist: sphinx; extra == "docs"
Requires-Dist: pydata-sphinx-theme; extra == "docs"
Requires-Dist: sphinx-autoapi; extra == "docs"
Requires-Dist: nbsphinx; extra == "docs"
Requires-Dist: ipython; extra == "docs"
Requires-Dist: pandoc; extra == "docs"
Requires-Dist: packaging; extra == "docs"
Provides-Extra: dev
Requires-Dist: solpolpy[docs,test]; extra == "dev"
Requires-Dist: pre-commit; extra == "dev"
Dynamic: license-file
